jupyter_threejs_sage/__init__.py
jupyter_threejs_sage/static/r122/three.min.js
jupyter_threejs_sage/static/r123/three.min.js
jupyter_threejs_sage/static/r130/three.min.js
jupyter_threejs_sage-130.data/data/share/jupyter/nbextensions/threejs-sage/r122/three.min.js
jupyter_threejs_sage-130.data/data/share/jupyter/nbextensions/threejs-sage/r123/three.min.js
jupyter_threejs_sage-130.data/data/share/jupyter/nbextensions/threejs-sage/r130/three.min.js
jupyter_threejs_sage-130.dist-info/LICENSE
jupyter_threejs_sage-130.dist-info/METADATA
jupyter_threejs_sage-130.dist-info/WHEEL
jupyter_threejs_sage-130.dist-info/top_level.txt
jupyter_threejs_sage-130.dist-info/RECORD
