Metadata-Version: 2.1
Name: jupyter-threejs-sage
Version: 130
Summary: Sage: Open Source Mathematics Software: Jupyter extension for 3D graphics with threejs
Author-email: The Sage Developers <sage-support@googlegroups.com>
License: MIT License
Project-URL: Homepage, https://github.com/sagemath/threejs-sage
Classifier: Development Status :: 6 - Mature
Classifier: Intended Audience :: Developers
Classifier: Intended Audience :: System Administrators
Classifier: Intended Audience :: Science/Research
Classifier: License :: OSI Approved :: MIT License
Classifier: Programming Language :: Python
Classifier: Programming Language :: Python :: 3
Classifier: Programming Language :: Python :: 3 :: Only
Classifier: Framework :: Jupyter
License-File: LICENSE
